elkm1_lib/__init__.py
elkm1_lib/areas.py
elkm1_lib/connection.py
elkm1_lib/const.py
elkm1_lib/counters.py
elkm1_lib/discovery.py
elkm1_lib/elements.py
elkm1_lib/elk.py
elkm1_lib/keypads.py
elkm1_lib/lights.py
elkm1_lib/message.py
elkm1_lib/notify.py
elkm1_lib/outputs.py
elkm1_lib/panel.py
elkm1_lib/py.typed
elkm1_lib/settings.py
elkm1_lib/tasks.py
elkm1_lib/thermostats.py
elkm1_lib/users.py
elkm1_lib/util.py
elkm1_lib/zones.py
elkm1_lib-2.2.11.dist-info/METADATA
elkm1_lib-2.2.11.dist-info/WHEEL
elkm1_lib-2.2.11.dist-info/licenses/LICENCE
elkm1_lib-2.2.11.dist-info/RECORD
