Metadata-Version: 2.4
Name: elkm1-lib
Version: 2.2.11
Summary: Library for interacting with ElkM1 alarm/automation panel.
Project-URL: Homepage, https://github.com/gwww/elkm1
Project-URL: Repository, https://github.com/gwww/elkm1.git
Project-URL: Issues, https://github.com/gwww/elkm1/issues
Author-email: Glenn Waters <gwwaters+elkm1@gmail.com>
License-File: LICENCE
Classifier: Development Status :: 5 - Production/Stable
Classifier: Intended Audience :: Developers
Classifier: License :: OSI Approved :: MIT License
Classifier: Programming Language :: Python :: 3.11
Classifier: Programming Language :: Python :: 3.12
Classifier: Topic :: Home Automation
Requires-Python: >=3.11
Requires-Dist: pyserial-asyncio-fast>=0.11
